{"STtMTo1TN/M+zxf/aFAuXQ==":"logomakr_3sxxzw-192x192.png","bg4I7MvjdcPpCeg2Rb068Q==":"1-1.gif","J+dtabVUJ3XrMsYxGib3Mg==":"%E5%9B%BE%E7%89%871-348x112.png","uRh8KT3tFdTHHcrR1emG2w==":"logomakr_0zpezn-556x593.png","TAypwRGm5NR/ZW0A3lgl/g==":"4.gif","t20vrSWfpNWxLLi+d0JLHQ==":"4).gif","2YoJZIeoPkRkx0tkKgklMw==":"%E5%9B%BE%E7%89%871-1014x325.png","iw6dLgJ0TCbSleFSUeVUOQ==":"logomakr_0zpezn-563x600.png","7mQwLLgHOo4gX2C1VYjY5A==":"mbr-1920x1280.jpg","4v8oVieAcbL7cnUsCtZXnA==":"mbr-1-1920x1280.jpg","gQw2QqMJaSqWArMgy+EBfg==":"mbr-1920x1080.jpg","bNUb0beCCmBbsKqOlHkX0w==":"mbr-2-1920x1280.jpg","BgGC2nPBT9qlSg2M3/0i/Q==":"mbr-1920x1279.jpg","8hdM9eke3uREEe+rfDRBBg==":"mbr-3-1920x1280.jpg","4/Ymeeku9hDLq+eL5aYZVw==":"1-2.gif","n0h1dU7ctASbCBYw2hEKwQ==":"8%20(1).gif","q0Do3wigHymvPs2hM6i+9Q==":"10.gif","yMVDtha9DCWwzBDSd2+S2A==":"11.gif","sQx10zO57ZuSrQql4OoJDw==":"1-3.gif","9WiHedk38zykwdlYIn0dAA==":"mbr-1280x720.jpg","dR3tEXNbCpcx/jKbITdZcA==":"%E5%9B%BE%E7%89%871-2000x1124.png","c1D2cGyKriyN+RGq4KdwnQ==":"2023-08-24-111701-2000x1046.png","36tNM68iyU1mvBSCNAIkYQ==":"ima-1280x720.png","WiV7v4/9BJYmwmlUnhnk/g==":"ezgif.com-video-to-gif.gif","KWQElE4aQ5/DcHGj4afU4Q==":"ezgif.com-optimize.gif","bYdTcir4EqEOqFZ2metE5A==":"2023-08-24-111808-2000x1046.png","mJl9KuWbXWHEM/5QvgE1rA==":"2023-08-24-111732-2000x1046.png","HLa4C6Gb4wHeuXVffEQ0EQ==":"2023-08-24-111923-2000x1046.png","JjgS8Z7zNOoSbOcvLEyIwg==":"2023-08-24-111832-2000x1046.png","2kOc7FgtoHo4rMgcl25e7Q==":"led%E6%98%BE%E7%A4%BA%E5%B1%8F-%E5%A5%8B%E6%96%97%E9%9D%92%E6%98%A5-8-2000x1143.png","nJC7mofvzNgpSaOvzMLW9Q==":"2a07ad00a958412c96b9f6bbc85f158b-600x450.png","4xvkQ7hKn7WiNql2UO6lrA==":"2023-08-24-162124-2000x1317.png","foys+jfTHQUUeVwATqtnRg==":"b82300657b8b4cb6b74acc2c9a5cf22c-600x450.png","bwYn0QX4tGNrFyrPEWpUPg==":"2023-08-24-162324-2000x1314.png","GZh20HqrmTUZBxLT6cDDAA==":"ezgif.com-video-to-gif.gif","nig/hQZFCjG4ANTTqD/RiQ==":"led%E6%98%BE%E7%A4%BA%E5%B1%8F-%E5%A5%8B%E6%96%97%E9%9D%92%E6%98%A5-8.png-1668x953.jpg","TUxYlyxcOXvt11ihA2Kf0w==":"2023-08-24-110911-1258x1079.png","Xf7DunyJC2g2a/PKto5vBA==":"%E7%AC%AC8%E9%A1%B5-21-1300x708.png","e96BK5xj5mKitnwBImbSYg==":"%E7%AC%AC8%E9%A1%B5-20-1366x603.png","h2o6rRjVPSGo/ieOLw/h7w==":"%E7%AC%AC3%E9%A1%B5-11-512x393.png","fm7s+77xFTaEHeaoZVh9rA==":"%E7%AC%AC45%E9%A1%B5-99-669x376.png","T/hcMB72hHPjuOd9kfu1Cg==":"%E7%AC%AC3%E9%A1%B5-4-518x389.png","jYRFq6DmzwoPRJUVTNS7kA==":"%E7%AC%AC3%E9%A1%B5-8-512x353.png","erGjSBEXjpBm07ibVygb2Q==":"%E7%AC%AC5%E9%A1%B5-19-565x424.png","GkSoLQ0nV1k5ml5r9IbscA==":"kappframework-nlaksw(1)(1)-2000x1367.png","qIi6IE+K5sOCBhEwYRH/hw==":"%E7%AC%AC5%E9%A1%B5-22-531x398.png","afFbPAyBiy5G+RIZd/l7jg==":"%E7%AC%AC5%E9%A1%B5-24-597x398.png","6rAXeslKNTJ9Gbrp54LLJA==":"%E7%AC%AC6%E9%A1%B5-28-710x473.png","yFSbOLitElPov97alJxYHA==":"%E7%AC%AC6%E9%A1%B5-29-710x473.png","4LewEPA75fqXf6mjEj1Y6Q==":"%E7%AC%AC6%E9%A1%B5-31-710x473.png","ZhwgrpzWRDYxCdruZsIU8g==":"%E7%AC%AC6%E9%A1%B5-27-710x399.png","3MiaMyd6iMl/o3wo7jninQ==":"kappframework-vkfqvt(1)(1)-1404x790.png","Q0uwVznY+3uUm9sBYALt+w==":"kappframework-gvxjyw(1)(1)-624x432.png","FAlA9pQsvZJvMDNrpKf2Vw==":"9412224ec8157224a38f44004842643-611x336.jpg","vHiugRGlEIEGxtfJrzQPsw==":"d3e372c2f6dc7839a3cddb81d865cac-1280x959.jpg","zNgQcSOoB1NksHj4+OJTRw==":"kappframework-hrssea(1)(1)-618x428.png","PZiXL+5TAfoLO2zi3NNuVA==":"%E5%9E%83%E5%9C%BE%E5%88%86%E7%B1%BB%E7%AB%8B%E4%BD%93%E5%8C%96%E5%AE%A3%E6%95%99%E5%B7%A5%E4%BD%9C-14-2000x1125.png","UC4gP+gvIZce2J4yGkN0+g==":"%E6%88%91%E5%B8%82%E4%B8%BE%E5%8A%9E%E7%94%9F%E6%B4%BB%E5%9E%83%E5%9C%BE%E5%88%86%E7%B1%BB%E4%B8%BB%E9%A2%98%E7%9F%A5%E8%AF%86%E7%AB%9E%E8%B5%9B-960x540.jpg","4aTr+zL1jRSst8JXCppO9Q==":"%E6%88%91%E5%B8%82%E4%B8%BE%E5%8A%9E%E7%94%9F%E6%B4%BB%E5%9E%83%E5%9C%BE%E5%88%86%E7%B1%BB%E4%B8%BB%E9%A2%98%E7%9F%A5%E8%AF%86%E7%AB%9E%E8%B5%9B11-960x540.jpg","qzRfm7pFJVuIprf8gSjIKg==":"kappframework-auhvox(1)(1)-908x408.png","9LSfaBxNDf5eA91YtgV7bw==":"kappframework-ltnalw(1)(1)-904x406.png","hqJs7ALP7dOWPrjFbZ6tjA==":"kappframework-mhechb(1)(1)-904x406.png","+2/RFA9dQmlve+c/0DUiSw==":"kappframework-jguesw(1)(1)-904x406.png","jDkk90+/V2lDHbo2zcNH5Q==":"kappframework-vzhamn(1)(1)-904x406.png","js430WlhPMZr/Q1gxnNMYg==":"kappframework-xthioa(1)(1)-908x408.png","87cNaEohCJ1D9kuLRJmlzA==":"kappframework-ykahet(1)(1)-904x406.png","mABelsQzm+N+QTfybQl5yA==":"kappframework-stfogg(1)(1)-852x384.png","hAVvGSrLzA8D0LPns3Tm0A==":"kappframework-dplfdu(1)(1)-852x384.png","Uz30rv1L+Bko3JNfPimcwQ==":"kappframework-hvnikf(1)(1)-852x384.png","pdXpa90AxJmrNkXNOuZW9A==":"kappframework-hzthcp(1)(1)-852x384.png","71Hbm/llDo9ERLML1bFkkg==":"kappframework-igmlnw(1)(1)-852x384.png","gYW5WKLEqLbV4mXjzOi4Kw==":"kappframework-qfcsln(1)(1)-852x384.png","1Ne3Fi0ZArbzH62SQazPsw==":"2023-08-24-111808-2000x1046.jpg","LJuJBkHY3QfOuMaouMJq4g==":"led-8.png-1-1668x953.jpg","EMconFlJkIMUgvv0DFQehQ==":"3-11-512x393.jpg","S0K2tdrsO6578BnPAmS8aQ==":"kappframework-vkfqvt(1)(1)-1404x790.jpg","lwOL3n3PTvYfEp46Fja+1w==":"kappframework-gvxjyw(1)(1)-624x432.jpg","mq9iMa8SDKor2jsDU4Lerg==":"kappframework-auhvox11-908x408.jpg","AZ3HATttP4Ayyqx+oFNkwA==":"kappframework-stfogg(1)(1)-852x384.jpg"}